remotestatsclient/__init__.py
remotestatsclient/__main__.py
remotestatsclient/monitor.py
remotestatsclient/remotestatsclient.py
remotestatsclient-0.1.0.dist-info/DESCRIPTION.rst
remotestatsclient-0.1.0.dist-info/METADATA
remotestatsclient-0.1.0.dist-info/RECORD
remotestatsclient-0.1.0.dist-info/WHEEL
remotestatsclient-0.1.0.dist-info/entry_points.txt
remotestatsclient-0.1.0.dist-info/metadata.json
remotestatsclient-0.1.0.dist-info/top_level.txt
