Metadata-Version: 2.0
Name: remotestatsclient
Version: 0.1.0
Summary: RemoteStats makes possible to inspect realtime information about a remote machine using a browser. This is the client to be installed in such machine.
Home-page: https://github.com/hugombarreto/remotestatsclient
Author: Hugo Sadok
Author-email: hugo@sadok.com.br
License: ISCL
Keywords: remotestatsclient
Platform: UNKNOWN
Classifier: Development Status :: 2 - Pre-Alpha
Classifier: Intended Audience :: Developers
Classifier: License :: OSI Approved :: ISC License (ISCL)
Classifier: Natural Language :: English
Classifier: Programming Language :: Python :: 2
Classifier: Programming Language :: Python :: 2.6
Classifier: Programming Language :: Python :: 2.7
Classifier: Programming Language :: Python :: 3
Classifier: Programming Language :: Python :: 3.3
Classifier: Programming Language :: Python :: 3.4
Classifier: Programming Language :: Python :: 3.5
Requires-Dist: psutil
Requires-Dist: requests
